Metadata-Version: 2.1
Name: op-mewtwo
Version: 0.1
Summary: mewtwo - RiskDataframe
Home-page: https://github.com/PaulaEscusol/Group-assignment_Python-II
Author: Ahmed Aljeshi | Juan Francisco Balbi | Paula Escusol Entio | Isobel Rae Impas | Paliz Mungkaladung
Author-email: paliz.mungkaladung@student.ie.edu
License: MIT
Platform: UNKNOWN
Classifier: Programming Language :: Python :: 3
Classifier: License :: OSI Approved :: MIT License
Classifier: Operating System :: OS Independent
